[{"name":"proxy_recrypt","qualifiedName":"proxy_recrypt","href":"proxy_recrypt/","kind":9,"packageRank":0,"desc":""},{"name":"Capsule","qualifiedName":"proxy_recrypt.Capsule","href":"proxy_recrypt/Capsule-class.html","kind":3,"packageRank":0,"desc":"A class representing an encryption capsule","enclosedBy":{"name":"proxy_recrypt","kind":9,"href":"proxy_recrypt/"}},{"name":"Capsule.new","qualifiedName":"proxy_recrypt.Capsule.Capsule.new","href":"proxy_recrypt/Capsule/Capsule.html","kind":2,"packageRank":0,"desc":"","enclosedBy":{"name":"Capsule","kind":3,"href":"proxy_recrypt/Capsule-class.html"}},{"name":"E","qualifiedName":"proxy_recrypt.Capsule.E","href":"proxy_recrypt/Capsule/E.html","kind":16,"overriddenDepth":0,"packageRank":0,"desc":"","enclosedBy":{"name":"Capsule","kind":3,"href":"proxy_recrypt/Capsule-class.html"}},{"name":"S","qualifiedName":"proxy_recrypt.Capsule.S","href":"proxy_recrypt/Capsule/S.html","kind":16,"overriddenDepth":0,"packageRank":0,"desc":"","enclosedBy":{"name":"Capsule","kind":3,"href":"proxy_recrypt/Capsule-class.html"}},{"name":"V","qualifiedName":"proxy_recrypt.Capsule.V","href":"proxy_recrypt/Capsule/V.html","kind":16,"overriddenDepth":0,"packageRank":0,"desc":"","enclosedBy":{"name":"Capsule","kind":3,"href":"proxy_recrypt/Capsule-class.html"}},{"name":"XG","qualifiedName":"proxy_recrypt.Capsule.XG","href":"proxy_recrypt/Capsule/XG.html","kind":16,"overriddenDepth":0,"packageRank":0,"desc":"","enclosedBy":{"name":"Capsule","kind":3,"href":"proxy_recrypt/Capsule-class.html"}},{"name":"fromBase64","qualifiedName":"proxy_recrypt.Capsule.fromBase64","href":"proxy_recrypt/Capsule/fromBase64.html","kind":10,"overriddenDepth":0,"packageRank":0,"desc":"Create a Capsule from base64 string","enclosedBy":{"name":"Capsule","kind":3,"href":"proxy_recrypt/Capsule-class.html"}},{"name":"isReEncrypted","qualifiedName":"proxy_recrypt.Capsule.isReEncrypted","href":"proxy_recrypt/Capsule/isReEncrypted.html","kind":16,"overriddenDepth":0,"packageRank":0,"desc":"","enclosedBy":{"name":"Capsule","kind":3,"href":"proxy_recrypt/Capsule-class.html"}},{"name":"params","qualifiedName":"proxy_recrypt.Capsule.params","href":"proxy_recrypt/Capsule/params.html","kind":16,"overriddenDepth":0,"packageRank":0,"desc":"","enclosedBy":{"name":"Capsule","kind":3,"href":"proxy_recrypt/Capsule-class.html"}},{"name":"toBase64","qualifiedName":"proxy_recrypt.Capsule.toBase64","href":"proxy_recrypt/Capsule/toBase64.html","kind":10,"overriddenDepth":0,"packageRank":0,"desc":"Convert Capsule to base64 string","enclosedBy":{"name":"Capsule","kind":3,"href":"proxy_recrypt/Capsule-class.html"}},{"name":"GroupElement","qualifiedName":"proxy_recrypt.GroupElement","href":"proxy_recrypt/GroupElement-class.html","kind":3,"packageRank":0,"desc":"A class representing a point on the elliptic curve","enclosedBy":{"name":"proxy_recrypt","kind":9,"href":"proxy_recrypt/"}},{"name":"GroupElement.new","qualifiedName":"proxy_recrypt.GroupElement.GroupElement.new","href":"proxy_recrypt/GroupElement/GroupElement.html","kind":2,"packageRank":0,"desc":"","enclosedBy":{"name":"GroupElement","kind":3,"href":"proxy_recrypt/GroupElement-class.html"}},{"name":"add","qualifiedName":"proxy_recrypt.GroupElement.add","href":"proxy_recrypt/GroupElement/add.html","kind":10,"overriddenDepth":0,"packageRank":0,"desc":"Add two group elements","enclosedBy":{"name":"GroupElement","kind":3,"href":"proxy_recrypt/GroupElement-class.html"}},{"name":"fromBytes","qualifiedName":"proxy_recrypt.GroupElement.fromBytes","href":"proxy_recrypt/GroupElement/fromBytes.html","kind":10,"overriddenDepth":0,"packageRank":0,"desc":"Create a GroupElement from bytes","enclosedBy":{"name":"GroupElement","kind":3,"href":"proxy_recrypt/GroupElement-class.html"}},{"name":"mul","qualifiedName":"proxy_recrypt.GroupElement.mul","href":"proxy_recrypt/GroupElement/mul.html","kind":10,"overriddenDepth":0,"packageRank":0,"desc":"Multiply a group element by a scalar","enclosedBy":{"name":"GroupElement","kind":3,"href":"proxy_recrypt/GroupElement-class.html"}},{"name":"params","qualifiedName":"proxy_recrypt.GroupElement.params","href":"proxy_recrypt/GroupElement/params.html","kind":16,"overriddenDepth":0,"packageRank":0,"desc":"","enclosedBy":{"name":"GroupElement","kind":3,"href":"proxy_recrypt/GroupElement-class.html"}},{"name":"point","qualifiedName":"proxy_recrypt.GroupElement.point","href":"proxy_recrypt/GroupElement/point.html","kind":16,"overriddenDepth":0,"packageRank":0,"desc":"","enclosedBy":{"name":"GroupElement","kind":3,"href":"proxy_recrypt/GroupElement-class.html"}},{"name":"toBytes","qualifiedName":"proxy_recrypt.GroupElement.toBytes","href":"proxy_recrypt/GroupElement/toBytes.html","kind":10,"overriddenDepth":0,"packageRank":0,"desc":"Convert GroupElement to bytes","enclosedBy":{"name":"GroupElement","kind":3,"href":"proxy_recrypt/GroupElement-class.html"}},{"name":"KeyPair","qualifiedName":"proxy_recrypt.KeyPair","href":"proxy_recrypt/KeyPair-class.html","kind":3,"packageRank":0,"desc":"A class representing a key pair","enclosedBy":{"name":"proxy_recrypt","kind":9,"href":"proxy_recrypt/"}},{"name":"KeyPair.new","qualifiedName":"proxy_recrypt.KeyPair.KeyPair.new","href":"proxy_recrypt/KeyPair/KeyPair.html","kind":2,"packageRank":0,"desc":"","enclosedBy":{"name":"KeyPair","kind":3,"href":"proxy_recrypt/KeyPair-class.html"}},{"name":"fromBase64","qualifiedName":"proxy_recrypt.KeyPair.fromBase64","href":"proxy_recrypt/KeyPair/fromBase64.html","kind":10,"overriddenDepth":0,"packageRank":0,"desc":"Create a KeyPair from base64 string","enclosedBy":{"name":"KeyPair","kind":3,"href":"proxy_recrypt/KeyPair-class.html"}},{"name":"fromJson","qualifiedName":"proxy_recrypt.KeyPair.fromJson","href":"proxy_recrypt/KeyPair/fromJson.html","kind":10,"overriddenDepth":0,"packageRank":0,"desc":"Create a KeyPair from JSON string","enclosedBy":{"name":"KeyPair","kind":3,"href":"proxy_recrypt/KeyPair-class.html"}},{"name":"fromPublicKeyBase64","qualifiedName":"proxy_recrypt.KeyPair.fromPublicKeyBase64","href":"proxy_recrypt/KeyPair/fromPublicKeyBase64.html","kind":10,"overriddenDepth":0,"packageRank":0,"desc":"Create a KeyPair with only the public key from base64 string","enclosedBy":{"name":"KeyPair","kind":3,"href":"proxy_recrypt/KeyPair-class.html"}},{"name":"privateKey","qualifiedName":"proxy_recrypt.KeyPair.privateKey","href":"proxy_recrypt/KeyPair/privateKey.html","kind":16,"overriddenDepth":0,"packageRank":0,"desc":"","enclosedBy":{"name":"KeyPair","kind":3,"href":"proxy_recrypt/KeyPair-class.html"}},{"name":"publicKey","qualifiedName":"proxy_recrypt.KeyPair.publicKey","href":"proxy_recrypt/KeyPair/publicKey.html","kind":16,"overriddenDepth":0,"packageRank":0,"desc":"","enclosedBy":{"name":"KeyPair","kind":3,"href":"proxy_recrypt/KeyPair-class.html"}},{"name":"publicKeyToBase64","qualifiedName":"proxy_recrypt.KeyPair.publicKeyToBase64","href":"proxy_recrypt/KeyPair/publicKeyToBase64.html","kind":10,"overriddenDepth":0,"packageRank":0,"desc":"Convert only the public key to base64 string","enclosedBy":{"name":"KeyPair","kind":3,"href":"proxy_recrypt/KeyPair-class.html"}},{"name":"toBase64","qualifiedName":"proxy_recrypt.KeyPair.toBase64","href":"proxy_recrypt/KeyPair/toBase64.html","kind":10,"overriddenDepth":0,"packageRank":0,"desc":"Convert KeyPair to base64 string (includes both private and public keys)","enclosedBy":{"name":"KeyPair","kind":3,"href":"proxy_recrypt/KeyPair-class.html"}},{"name":"toJson","qualifiedName":"proxy_recrypt.KeyPair.toJson","href":"proxy_recrypt/KeyPair/toJson.html","kind":10,"overriddenDepth":0,"packageRank":0,"desc":"Convert KeyPair to JSON string","enclosedBy":{"name":"KeyPair","kind":3,"href":"proxy_recrypt/KeyPair-class.html"}},{"name":"PrivateKey","qualifiedName":"proxy_recrypt.PrivateKey","href":"proxy_recrypt/PrivateKey-class.html","kind":3,"packageRank":0,"desc":"A class representing a private key","enclosedBy":{"name":"proxy_recrypt","kind":9,"href":"proxy_recrypt/"}},{"name":"PrivateKey.new","qualifiedName":"proxy_recrypt.PrivateKey.PrivateKey.new","href":"proxy_recrypt/PrivateKey/PrivateKey.html","kind":2,"packageRank":0,"desc":"","enclosedBy":{"name":"PrivateKey","kind":3,"href":"proxy_recrypt/PrivateKey-class.html"}},{"name":"fromBase64","qualifiedName":"proxy_recrypt.PrivateKey.fromBase64","href":"proxy_recrypt/PrivateKey/fromBase64.html","kind":10,"overriddenDepth":0,"packageRank":0,"desc":"Create a PrivateKey from base64 string","enclosedBy":{"name":"PrivateKey","kind":3,"href":"proxy_recrypt/PrivateKey-class.html"}},{"name":"fromBytes","qualifiedName":"proxy_recrypt.PrivateKey.fromBytes","href":"proxy_recrypt/PrivateKey/fromBytes.html","kind":10,"overriddenDepth":0,"packageRank":0,"desc":"Create a PrivateKey from bytes","enclosedBy":{"name":"PrivateKey","kind":3,"href":"proxy_recrypt/PrivateKey-class.html"}},{"name":"generate","qualifiedName":"proxy_recrypt.PrivateKey.generate","href":"proxy_recrypt/PrivateKey/generate.html","kind":10,"overriddenDepth":0,"packageRank":0,"desc":"Generate a new private key","enclosedBy":{"name":"PrivateKey","kind":3,"href":"proxy_recrypt/PrivateKey-class.html"}},{"name":"getPublicKey","qualifiedName":"proxy_recrypt.PrivateKey.getPublicKey","href":"proxy_recrypt/PrivateKey/getPublicKey.html","kind":10,"overriddenDepth":0,"packageRank":0,"desc":"Get the corresponding public key","enclosedBy":{"name":"PrivateKey","kind":3,"href":"proxy_recrypt/PrivateKey-class.html"}},{"name":"params","qualifiedName":"proxy_recrypt.PrivateKey.params","href":"proxy_recrypt/PrivateKey/params.html","kind":16,"overriddenDepth":0,"packageRank":0,"desc":"","enclosedBy":{"name":"PrivateKey","kind":3,"href":"proxy_recrypt/PrivateKey-class.html"}},{"name":"scalar","qualifiedName":"proxy_recrypt.PrivateKey.scalar","href":"proxy_recrypt/PrivateKey/scalar.html","kind":16,"overriddenDepth":0,"packageRank":0,"desc":"","enclosedBy":{"name":"PrivateKey","kind":3,"href":"proxy_recrypt/PrivateKey-class.html"}},{"name":"toBase64","qualifiedName":"proxy_recrypt.PrivateKey.toBase64","href":"proxy_recrypt/PrivateKey/toBase64.html","kind":10,"overriddenDepth":0,"packageRank":0,"desc":"Convert PrivateKey to base64 string","enclosedBy":{"name":"PrivateKey","kind":3,"href":"proxy_recrypt/PrivateKey-class.html"}},{"name":"toBytes","qualifiedName":"proxy_recrypt.PrivateKey.toBytes","href":"proxy_recrypt/PrivateKey/toBytes.html","kind":10,"overriddenDepth":0,"packageRank":0,"desc":"Convert PrivateKey to bytes","enclosedBy":{"name":"PrivateKey","kind":3,"href":"proxy_recrypt/PrivateKey-class.html"}},{"name":"PublicKey","qualifiedName":"proxy_recrypt.PublicKey","href":"proxy_recrypt/PublicKey-class.html","kind":3,"packageRank":0,"desc":"A class representing a public key","enclosedBy":{"name":"proxy_recrypt","kind":9,"href":"proxy_recrypt/"}},{"name":"PublicKey.new","qualifiedName":"proxy_recrypt.PublicKey.PublicKey.new","href":"proxy_recrypt/PublicKey/PublicKey.html","kind":2,"packageRank":0,"desc":"","enclosedBy":{"name":"PublicKey","kind":3,"href":"proxy_recrypt/PublicKey-class.html"}},{"name":"fromBase64","qualifiedName":"proxy_recrypt.PublicKey.fromBase64","href":"proxy_recrypt/PublicKey/fromBase64.html","kind":10,"overriddenDepth":0,"packageRank":0,"desc":"Create a PublicKey from base64 string","enclosedBy":{"name":"PublicKey","kind":3,"href":"proxy_recrypt/PublicKey-class.html"}},{"name":"params","qualifiedName":"proxy_recrypt.PublicKey.params","href":"proxy_recrypt/PublicKey/params.html","kind":16,"overriddenDepth":0,"packageRank":0,"desc":"","enclosedBy":{"name":"PublicKey","kind":3,"href":"proxy_recrypt/PublicKey-class.html"}},{"name":"point","qualifiedName":"proxy_recrypt.PublicKey.point","href":"proxy_recrypt/PublicKey/point.html","kind":16,"overriddenDepth":0,"packageRank":0,"desc":"","enclosedBy":{"name":"PublicKey","kind":3,"href":"proxy_recrypt/PublicKey-class.html"}},{"name":"toBase64","qualifiedName":"proxy_recrypt.PublicKey.toBase64","href":"proxy_recrypt/PublicKey/toBase64.html","kind":10,"overriddenDepth":0,"packageRank":0,"desc":"Convert PublicKey to base64 string","enclosedBy":{"name":"PublicKey","kind":3,"href":"proxy_recrypt/PublicKey-class.html"}},{"name":"ReEncryptionKey","qualifiedName":"proxy_recrypt.ReEncryptionKey","href":"proxy_recrypt/ReEncryptionKey-class.html","kind":3,"packageRank":0,"desc":"A class representing a re-encryption key","enclosedBy":{"name":"proxy_recrypt","kind":9,"href":"proxy_recrypt/"}},{"name":"ReEncryptionKey.new","qualifiedName":"proxy_recrypt.ReEncryptionKey.ReEncryptionKey.new","href":"proxy_recrypt/ReEncryptionKey/ReEncryptionKey.html","kind":2,"packageRank":0,"desc":"","enclosedBy":{"name":"ReEncryptionKey","kind":3,"href":"proxy_recrypt/ReEncryptionKey-class.html"}},{"name":"fromBase64","qualifiedName":"proxy_recrypt.ReEncryptionKey.fromBase64","href":"proxy_recrypt/ReEncryptionKey/fromBase64.html","kind":10,"overriddenDepth":0,"packageRank":0,"desc":"Create a ReEncryptionKey from base64 string","enclosedBy":{"name":"ReEncryptionKey","kind":3,"href":"proxy_recrypt/ReEncryptionKey-class.html"}},{"name":"params","qualifiedName":"proxy_recrypt.ReEncryptionKey.params","href":"proxy_recrypt/ReEncryptionKey/params.html","kind":16,"overriddenDepth":0,"packageRank":0,"desc":"","enclosedBy":{"name":"ReEncryptionKey","kind":3,"href":"proxy_recrypt/ReEncryptionKey-class.html"}},{"name":"point","qualifiedName":"proxy_recrypt.ReEncryptionKey.point","href":"proxy_recrypt/ReEncryptionKey/point.html","kind":16,"overriddenDepth":0,"packageRank":0,"desc":"","enclosedBy":{"name":"ReEncryptionKey","kind":3,"href":"proxy_recrypt/ReEncryptionKey-class.html"}},{"name":"scalar","qualifiedName":"proxy_recrypt.ReEncryptionKey.scalar","href":"proxy_recrypt/ReEncryptionKey/scalar.html","kind":16,"overriddenDepth":0,"packageRank":0,"desc":"","enclosedBy":{"name":"ReEncryptionKey","kind":3,"href":"proxy_recrypt/ReEncryptionKey-class.html"}},{"name":"toBase64","qualifiedName":"proxy_recrypt.ReEncryptionKey.toBase64","href":"proxy_recrypt/ReEncryptionKey/toBase64.html","kind":10,"overriddenDepth":0,"packageRank":0,"desc":"Convert ReEncryptionKey to base64 string","enclosedBy":{"name":"ReEncryptionKey","kind":3,"href":"proxy_recrypt/ReEncryptionKey-class.html"}},{"name":"Recrypt","qualifiedName":"proxy_recrypt.Recrypt","href":"proxy_recrypt/Recrypt-class.html","kind":3,"packageRank":0,"desc":"Main class for proxy re-encryption operations","enclosedBy":{"name":"proxy_recrypt","kind":9,"href":"proxy_recrypt/"}},{"name":"Recrypt.new","qualifiedName":"proxy_recrypt.Recrypt.Recrypt.new","href":"proxy_recrypt/Recrypt/Recrypt.html","kind":2,"packageRank":0,"desc":"","enclosedBy":{"name":"Recrypt","kind":3,"href":"proxy_recrypt/Recrypt-class.html"}},{"name":"decapsulate","qualifiedName":"proxy_recrypt.Recrypt.decapsulate","href":"proxy_recrypt/Recrypt/decapsulate.html","kind":10,"overriddenDepth":0,"packageRank":0,"desc":"Decapsulate a capsule with a private key","enclosedBy":{"name":"Recrypt","kind":3,"href":"proxy_recrypt/Recrypt-class.html"}},{"name":"encapsulate","qualifiedName":"proxy_recrypt.Recrypt.encapsulate","href":"proxy_recrypt/Recrypt/encapsulate.html","kind":10,"overriddenDepth":0,"packageRank":0,"desc":"Encapsulate a symmetric key for a public key","enclosedBy":{"name":"Recrypt","kind":3,"href":"proxy_recrypt/Recrypt-class.html"}},{"name":"generateKeyPair","qualifiedName":"proxy_recrypt.Recrypt.generateKeyPair","href":"proxy_recrypt/Recrypt/generateKeyPair.html","kind":10,"overriddenDepth":0,"packageRank":0,"desc":"Generate a new key pair","enclosedBy":{"name":"Recrypt","kind":3,"href":"proxy_recrypt/Recrypt-class.html"}},{"name":"generateReEncryptionKey","qualifiedName":"proxy_recrypt.Recrypt.generateReEncryptionKey","href":"proxy_recrypt/Recrypt/generateReEncryptionKey.html","kind":10,"overriddenDepth":0,"packageRank":0,"desc":"Generate a re-encryption key","enclosedBy":{"name":"Recrypt","kind":3,"href":"proxy_recrypt/Recrypt-class.html"}},{"name":"generateSecureRandomMessage","qualifiedName":"proxy_recrypt.Recrypt.generateSecureRandomMessage","href":"proxy_recrypt/Recrypt/generateSecureRandomMessage.html","kind":10,"overriddenDepth":0,"packageRank":0,"desc":"","enclosedBy":{"name":"Recrypt","kind":3,"href":"proxy_recrypt/Recrypt-class.html"}},{"name":"params","qualifiedName":"proxy_recrypt.Recrypt.params","href":"proxy_recrypt/Recrypt/params.html","kind":16,"overriddenDepth":0,"packageRank":0,"desc":"","enclosedBy":{"name":"Recrypt","kind":3,"href":"proxy_recrypt/Recrypt-class.html"}},{"name":"reEncrypt","qualifiedName":"proxy_recrypt.Recrypt.reEncrypt","href":"proxy_recrypt/Recrypt/reEncrypt.html","kind":10,"overriddenDepth":0,"packageRank":0,"desc":"Re-encrypt a capsule","enclosedBy":{"name":"Recrypt","kind":3,"href":"proxy_recrypt/Recrypt-class.html"}},{"name":"Scalar","qualifiedName":"proxy_recrypt.Scalar","href":"proxy_recrypt/Scalar-class.html","kind":3,"packageRank":0,"desc":"A class representing a scalar value in the elliptic curve field","enclosedBy":{"name":"proxy_recrypt","kind":9,"href":"proxy_recrypt/"}},{"name":"Scalar.new","qualifiedName":"proxy_recrypt.Scalar.Scalar.new","href":"proxy_recrypt/Scalar/Scalar.html","kind":2,"packageRank":0,"desc":"","enclosedBy":{"name":"Scalar","kind":3,"href":"proxy_recrypt/Scalar-class.html"}},{"name":"add","qualifiedName":"proxy_recrypt.Scalar.add","href":"proxy_recrypt/Scalar/add.html","kind":10,"overriddenDepth":0,"packageRank":0,"desc":"Add two scalars","enclosedBy":{"name":"Scalar","kind":3,"href":"proxy_recrypt/Scalar-class.html"}},{"name":"fromBytes","qualifiedName":"proxy_recrypt.Scalar.fromBytes","href":"proxy_recrypt/Scalar/fromBytes.html","kind":10,"overriddenDepth":0,"packageRank":0,"desc":"Create a Scalar from bytes","enclosedBy":{"name":"Scalar","kind":3,"href":"proxy_recrypt/Scalar-class.html"}},{"name":"inv","qualifiedName":"proxy_recrypt.Scalar.inv","href":"proxy_recrypt/Scalar/inv.html","kind":10,"overriddenDepth":0,"packageRank":0,"desc":"Get multiplicative inverse","enclosedBy":{"name":"Scalar","kind":3,"href":"proxy_recrypt/Scalar-class.html"}},{"name":"mul","qualifiedName":"proxy_recrypt.Scalar.mul","href":"proxy_recrypt/Scalar/mul.html","kind":10,"overriddenDepth":0,"packageRank":0,"desc":"Multiply two scalars","enclosedBy":{"name":"Scalar","kind":3,"href":"proxy_recrypt/Scalar-class.html"}},{"name":"order","qualifiedName":"proxy_recrypt.Scalar.order","href":"proxy_recrypt/Scalar/order.html","kind":16,"overriddenDepth":0,"packageRank":0,"desc":"","enclosedBy":{"name":"Scalar","kind":3,"href":"proxy_recrypt/Scalar-class.html"}},{"name":"toBytes","qualifiedName":"proxy_recrypt.Scalar.toBytes","href":"proxy_recrypt/Scalar/toBytes.html","kind":10,"overriddenDepth":0,"packageRank":0,"desc":"Convert Scalar to bytes","enclosedBy":{"name":"Scalar","kind":3,"href":"proxy_recrypt/Scalar-class.html"}},{"name":"value","qualifiedName":"proxy_recrypt.Scalar.value","href":"proxy_recrypt/Scalar/value.html","kind":16,"overriddenDepth":0,"packageRank":0,"desc":"","enclosedBy":{"name":"Scalar","kind":3,"href":"proxy_recrypt/Scalar-class.html"}},{"name":"SharedEncryptor","qualifiedName":"proxy_recrypt.SharedEncryptor","href":"proxy_recrypt/SharedEncryptor-class.html","kind":3,"packageRank":0,"desc":"A class representing a shared key that can be used for encryption and decryption.","enclosedBy":{"name":"proxy_recrypt","kind":9,"href":"proxy_recrypt/"}},{"name":"SharedEncryptor.new","qualifiedName":"proxy_recrypt.SharedEncryptor.SharedEncryptor.new","href":"proxy_recrypt/SharedEncryptor/SharedEncryptor.html","kind":2,"packageRank":0,"desc":"Creates a new shared key with the given components.","enclosedBy":{"name":"SharedEncryptor","kind":3,"href":"proxy_recrypt/SharedEncryptor-class.html"}},{"name":"capsule","qualifiedName":"proxy_recrypt.SharedEncryptor.capsule","href":"proxy_recrypt/SharedEncryptor/capsule.html","kind":16,"overriddenDepth":0,"packageRank":0,"desc":"","enclosedBy":{"name":"SharedEncryptor","kind":3,"href":"proxy_recrypt/SharedEncryptor-class.html"}},{"name":"createSharableEncryptor","qualifiedName":"proxy_recrypt.SharedEncryptor.createSharableEncryptor","href":"proxy_recrypt/SharedEncryptor/createSharableEncryptor.html","kind":10,"overriddenDepth":0,"packageRank":0,"desc":"Generates a new shared key using the given public key.","enclosedBy":{"name":"SharedEncryptor","kind":3,"href":"proxy_recrypt/SharedEncryptor-class.html"}},{"name":"decrypt","qualifiedName":"proxy_recrypt.SharedEncryptor.decrypt","href":"proxy_recrypt/SharedEncryptor/decrypt.html","kind":10,"overriddenDepth":0,"packageRank":0,"desc":"Decrypts a message using the shared key.","enclosedBy":{"name":"SharedEncryptor","kind":3,"href":"proxy_recrypt/SharedEncryptor-class.html"}},{"name":"encrypt","qualifiedName":"proxy_recrypt.SharedEncryptor.encrypt","href":"proxy_recrypt/SharedEncryptor/encrypt.html","kind":10,"overriddenDepth":0,"packageRank":0,"desc":"Encrypts a message using the shared key.","enclosedBy":{"name":"SharedEncryptor","kind":3,"href":"proxy_recrypt/SharedEncryptor-class.html"}},{"name":"encryptAndPackage","qualifiedName":"proxy_recrypt.SharedEncryptor.encryptAndPackage","href":"proxy_recrypt/SharedEncryptor/encryptAndPackage.html","kind":10,"overriddenDepth":0,"packageRank":0,"desc":"Encrypts a message and packages it with all necessary components for transmission.","enclosedBy":{"name":"SharedEncryptor","kind":3,"href":"proxy_recrypt/SharedEncryptor-class.html"}},{"name":"fromBase64","qualifiedName":"proxy_recrypt.SharedEncryptor.fromBase64","href":"proxy_recrypt/SharedEncryptor/fromBase64.html","kind":10,"overriddenDepth":0,"packageRank":0,"desc":"Deserializes a shared key from a base64 string.","enclosedBy":{"name":"SharedEncryptor","kind":3,"href":"proxy_recrypt/SharedEncryptor-class.html"}},{"name":"iv","qualifiedName":"proxy_recrypt.SharedEncryptor.iv","href":"proxy_recrypt/SharedEncryptor/iv.html","kind":16,"overriddenDepth":0,"packageRank":0,"desc":"","enclosedBy":{"name":"SharedEncryptor","kind":3,"href":"proxy_recrypt/SharedEncryptor-class.html"}},{"name":"key","qualifiedName":"proxy_recrypt.SharedEncryptor.key","href":"proxy_recrypt/SharedEncryptor/key.html","kind":16,"overriddenDepth":0,"packageRank":0,"desc":"","enclosedBy":{"name":"SharedEncryptor","kind":3,"href":"proxy_recrypt/SharedEncryptor-class.html"}},{"name":"toBase64","qualifiedName":"proxy_recrypt.SharedEncryptor.toBase64","href":"proxy_recrypt/SharedEncryptor/toBase64.html","kind":10,"overriddenDepth":0,"packageRank":0,"desc":"Serializes the shared key to a base64 string.","enclosedBy":{"name":"SharedEncryptor","kind":3,"href":"proxy_recrypt/SharedEncryptor-class.html"}},{"name":"unpackAndDecrypt","qualifiedName":"proxy_recrypt.SharedEncryptor.unpackAndDecrypt","href":"proxy_recrypt/SharedEncryptor/unpackAndDecrypt.html","kind":10,"overriddenDepth":0,"packageRank":0,"desc":"Unpacks and decrypts a message that was packaged using encryptAndPackage.","enclosedBy":{"name":"SharedEncryptor","kind":3,"href":"proxy_recrypt/SharedEncryptor-class.html"}},{"name":"withCapsule","qualifiedName":"proxy_recrypt.SharedEncryptor.withCapsule","href":"proxy_recrypt/SharedEncryptor/withCapsule.html","kind":10,"overriddenDepth":0,"packageRank":0,"desc":"Creates a copy of this shared key with a new capsule.","enclosedBy":{"name":"SharedEncryptor","kind":3,"href":"proxy_recrypt/SharedEncryptor-class.html"}},{"name":"defaultCurve","qualifiedName":"proxy_recrypt.defaultCurve","href":"proxy_recrypt/defaultCurve-constant.html","kind":19,"packageRank":0,"desc":"","enclosedBy":{"name":"proxy_recrypt","kind":9,"href":"proxy_recrypt/"}}]
